flowbber/__init__.py
flowbber/__main__.py
flowbber/args.py
flowbber/config.py
flowbber/inputs.py
flowbber/local.py
flowbber/logging.py
flowbber/main.py
flowbber/namespaces.py
flowbber/pipeline.py
flowbber/scheduler.py
flowbber/schema.py
flowbber/components/__init__.py
flowbber/components/aggregator.py
flowbber/components/base.py
flowbber/components/sink.py
flowbber/components/source.py
flowbber/data/config.json
flowbber/loaders/__init__.py
flowbber/loaders/aggregator.py
flowbber/loaders/loader.py
flowbber/loaders/sink.py
flowbber/loaders/source.py
flowbber/plugins/__init__.py
flowbber/plugins/aggregators/__init__.py
flowbber/plugins/aggregators/expander.py
flowbber/plugins/aggregators/filter.py
flowbber/plugins/aggregators/lcov_merger.py
flowbber/plugins/sinks/__init__.py
flowbber/plugins/sinks/archive.py
flowbber/plugins/sinks/data_splitter.py
flowbber/plugins/sinks/influxdb.py
flowbber/plugins/sinks/lcov_html.py
flowbber/plugins/sinks/mongodb.py
flowbber/plugins/sinks/print.py
flowbber/plugins/sinks/template.py
flowbber/plugins/sources/__init__.py
flowbber/plugins/sources/cobertura.py
flowbber/plugins/sources/config.py
flowbber/plugins/sources/cpu.py
flowbber/plugins/sources/env.py
flowbber/plugins/sources/git.py
flowbber/plugins/sources/github.py
flowbber/plugins/sources/gtest.py
flowbber/plugins/sources/json.py
flowbber/plugins/sources/lcov.py
flowbber/plugins/sources/pytest.py
flowbber/plugins/sources/sloc.py
flowbber/plugins/sources/speed.py
flowbber/plugins/sources/timestamp.py
flowbber/plugins/sources/user.py
flowbber/plugins/sources/valgrind/__init__.py
flowbber/plugins/sources/valgrind/drd.py
flowbber/plugins/sources/valgrind/helgrind.py
flowbber/plugins/sources/valgrind/memcheck.py
flowbber/utils/__init__.py
flowbber/utils/command.py
flowbber/utils/filter.py
flowbber/utils/git.py
flowbber/utils/iso8601.py
flowbber/utils/types.py
flowbber-1.11.0.data/scripts/flowbber
flowbber-1.11.0.dist-info/LICENSE
flowbber-1.11.0.dist-info/METADATA
flowbber-1.11.0.dist-info/WHEEL
flowbber-1.11.0.dist-info/entry_points.txt
flowbber-1.11.0.dist-info/top_level.txt
flowbber-1.11.0.dist-info/RECORD
