Metadata-Version: 2.1
Name: flowbber
Version: 1.11.0
Summary: Flowbber is a generic tool and framework that allows to execute custom pipelines for data gathering, publishing and analysis.
Home-page: https://docs.kuralabs.io/flowbber/
Author: KuraLabs S.R.L
Author-email: info@kuralabs.io
License: UNKNOWN
Keywords: flowbber
Platform: UNKNOWN
Classifier: Development Status :: 5 - Production/Stable
Classifier: Intended Audience :: Developers
Classifier: License :: OSI Approved :: Apache Software License
Classifier: Natural Language :: English
Classifier: Operating System :: POSIX :: Linux
Classifier: Programming Language :: Python :: 3
Requires-Dist: toml
Requires-Dist: ujson
Requires-Dist: pyyaml
Requires-Dist: colorlog
Requires-Dist: pprintpp
Requires-Dist: cerberus (>=1.3.1)
Requires-Dist: setuptools
Requires-Dist: pytimeparse
Requires-Dist: setproctitle
Provides-Extra: archive
Provides-Extra: cobertura
Requires-Dist: pycobertura ; extra == 'cobertura'
Provides-Extra: config
Provides-Extra: cpu
Requires-Dist: psutil ; extra == 'cpu'
Provides-Extra: data_splitter
Provides-Extra: env
Provides-Extra: expander
Provides-Extra: filter
Provides-Extra: git
Provides-Extra: github
Requires-Dist: pygithub ; extra == 'github'
Provides-Extra: gtest
Provides-Extra: influx
Requires-Dist: influxdb ; extra == 'influx'
Provides-Extra: json
Provides-Extra: lcov
Requires-Dist: lcov-cobertura ; extra == 'lcov'
Provides-Extra: lcov_html
Provides-Extra: lcov_merger
Requires-Dist: lcov-cobertura ; extra == 'lcov_merger'
Provides-Extra: mongo
Requires-Dist: pymongo ; extra == 'mongo'
Provides-Extra: print
Provides-Extra: pytest
Provides-Extra: sloc
Requires-Dist: pygount ; extra == 'sloc'
Provides-Extra: speed
Requires-Dist: pyspeedtest ; extra == 'speed'
Provides-Extra: template
Requires-Dist: jinja2 ; extra == 'template'
Provides-Extra: timestamp
Provides-Extra: user
Provides-Extra: valgrind_memcheck
Requires-Dist: xmltodict ; extra == 'valgrind_memcheck'
